odoo8_addon_web_search_datetime_completion-8.0.1.0.0.99.dev9-py2.7-nspkg.pth
odoo8_addon_web_search_datetime_completion-8.0.1.0.0.99.dev9.dist-info/DESCRIPTION.rst
odoo8_addon_web_search_datetime_completion-8.0.1.0.0.99.dev9.dist-info/METADATA
odoo8_addon_web_search_datetime_completion-8.0.1.0.0.99.dev9.dist-info/RECORD
odoo8_addon_web_search_datetime_completion-8.0.1.0.0.99.dev9.dist-info/WHEEL
odoo8_addon_web_search_datetime_completion-8.0.1.0.0.99.dev9.dist-info/metadata.json
odoo8_addon_web_search_datetime_completion-8.0.1.0.0.99.dev9.dist-info/namespace_packages.txt
odoo8_addon_web_search_datetime_completion-8.0.1.0.0.99.dev9.dist-info/top_level.txt
odoo_addons/web_search_datetime_completion/README.rst
odoo_addons/web_search_datetime_completion/__init__.py
odoo_addons/web_search_datetime_completion/__openerp__.py
odoo_addons/web_search_datetime_completion/i18n/es.po
odoo_addons/web_search_datetime_completion/i18n/fi.po
odoo_addons/web_search_datetime_completion/i18n/fr.po
odoo_addons/web_search_datetime_completion/i18n/it.po
odoo_addons/web_search_datetime_completion/i18n/pt_BR.po
odoo_addons/web_search_datetime_completion/i18n/sl.po
odoo_addons/web_search_datetime_completion/i18n/tr.po
odoo_addons/web_search_datetime_completion/i18n/web_search_datetime_completion.pot
odoo_addons/web_search_datetime_completion/static/description/icon.png
odoo_addons/web_search_datetime_completion/static/src/img/datetime_completion.png
odoo_addons/web_search_datetime_completion/static/src/js/web_search_datetime_completion.js
odoo_addons/web_search_datetime_completion/views/templates.xml
